simple_cfdi/__init__.py
simple_cfdi/spec/__init__.py
simple_cfdi/spec/comprobante.py
simple_cfdi/spec/timbre_fiscal_digital.py
tests/__init__.py
tests/test_xml_import_export.py
tests/utils.py
simple_cfdi-0.0.1.dist-info/LICENSE
simple_cfdi-0.0.1.dist-info/METADATA
simple_cfdi-0.0.1.dist-info/WHEEL
simple_cfdi-0.0.1.dist-info/top_level.txt
simple_cfdi-0.0.1.dist-info/RECORD
